foobar/__init__.py
foobar/cli.py
flit_foobar_tddschn-0.1.0.dist-info/entry_points.txt
flit_foobar_tddschn-0.1.0.dist-info/LICENSE
flit_foobar_tddschn-0.1.0.dist-info/WHEEL
flit_foobar_tddschn-0.1.0.dist-info/METADATA
flit_foobar_tddschn-0.1.0.dist-info/RECORD
