Metadata-Version: 2.1
Name: flit-foobar-tddschn
Version: 0.1.0
Summary: An amazing sample package!
Author-email: Xinyuan Chen <45612704+tddschn@users.noreply.github.com>
Classifier: License :: OSI Approved :: MIT License
